mswg/__init__.py
mswg/builder.py
koyash-0.0.1.dist-info/LICENSE
koyash-0.0.1.dist-info/METADATA
koyash-0.0.1.dist-info/WHEEL
koyash-0.0.1.dist-info/top_level.txt
koyash-0.0.1.dist-info/RECORD
