Metadata-Version: 2.1
Name: koyash
Version: 0.0.1
Summary: This is a Python app to create your own static websites.
Home-page: https://github.com/MrGranddy/koyash
Author: Vahit Buğra Yeşilkaynak
Author-email: bugrayesilkaynak@gmail.com
License: UNKNOWN
Project-URL: Bug Tracker, https://github.com/MrGranddy/koyash/issues
Platform: UNKNOWN
Classifier: Programming Language :: Python :: 3
Classifier: License :: OSI Approved :: MIT License
Classifier: Operating System :: OS Independent
Requires-Python: >=3.6
License-File: LICENSE
